{"somef_provenance": {"somef_version": "0.9.12", "somef_schema_version": "1.0.0", "date": "2025-11-17 11:57:45"}, "code_repository": [{"result": {"value": "https://github.com/LanguageMachines/dimbl", "type": "Url"}, "confidence": 1, "technique": "GitHub_API"}], "owner": [{"result": {"value": "LanguageMachines", "type": "Organization"}, "confidence": 1, "technique": "GitHub_API"}], "date_created": [{"result": {"value": "2015-11-23T11:18:25Z", "type": "Date"}, "confidence": 1, "technique": "GitHub_API"}], "date_updated": [{"result": {"value": "2025-09-08T10:58:01Z", "type": "Date"}, "confidence": 1, "technique": "GitHub_API"}], "license": [{"result": {"value": "https://api.github.com/licenses/gpl-3.0", "type": "License", "name": "GNU General Public License v3.0", "url": "https://api.github.com/licenses/gpl-3.0", "spdx_id": "GPL-3.0"}, "confidence": 1, "technique": "GitHub_API"}], "description": [{"result": {"value": "Distributed Tilburg Memory Based Learner", "type": "String"}, "confidence": 1, "technique": "GitHub_API"}], "name": [{"result": {"value": "dimbl", "type": "String"}, "confidence": 1, "technique": "GitHub_API"}], "full_name": [{"result": {"value": "LanguageMachines/dimbl", "type": "String"}, "confidence": 1, "technique": "GitHub_API"}], "issue_tracker": [{"result": {"value": "https://api.github.com/repos/LanguageMachines/dimbl/issues", "type": "Url"}, "confidence": 1, "technique": "GitHub_API"}], "forks_url": [{"result": {"value": "https://api.github.com/repos/LanguageMachines/dimbl/forks", "type": "Url"}, "confidence": 1, "technique": "GitHub_API"}], "stargazers_count": [{"result": {"value": 2, "type": "Number"}, "confidence": 1, "technique": "GitHub_API"}], "keywords": [{"result": {"value": "cpp, memory-based-learning, multithreading", "type": "String"}, "confidence": 1, "technique": "GitHub_API"}], "forks_count": [{"result": {"value": 2, "type": "Number"}, "confidence": 1, "technique": "GitHub_API"}], "homepage": [{"result": {"value": "https://languagemachines.github.io/timbl", "type": "Url"}, "confidence": 1, "technique": "GitHub_API"}], "download_url": [{"result": {"value": "https://github.com/LanguageMachines/dimbl/releases", "type": "Url"}, "confidence": 1, "technique": "GitHub_API"}], "programming_languages": [{"result": {"value": "C++", "name": "C++", "type": "Programming_language", "size": 29944}, "confidence": 1, "technique": "GitHub_API"}, {"result": {"value": "M4", "name": "M4", "type": "Programming_language", "size": 12987}, "confidence": 1, "technique": "GitHub_API"}, {"result": {"value": "Shell", "name": "Shell", "type": "Programming_language", "size": 2870}, "confidence": 1, "technique": "GitHub_API"}, {"result": {"value": "Makefile", "name": "Makefile", "type": "Programming_language", "size": 527}, "confidence": 1, "technique": "GitHub_API"}], "releases": [{"result": {"type": "Release", "value": "https://api.github.com/repos/LanguageMachines/dimbl/releases/190947850", "tag": "v0.18", "name": "v0.18", "author": {"name": "kosloot", "type": "User"}, "description": "* require C++17\r\n* some code refactoring\r\n* updated GitHub CI\r\n\r\n", "tarball_url": "https://api.github.com/repos/LanguageMachines/dimbl/tarball/v0.18", "zipball_url": "https://api.github.com/repos/LanguageMachines/dimbl/zipball/v0.18", "html_url": "https://github.com/LanguageMachines/dimbl/releases/tag/v0.18", "url": "https://api.github.com/repos/LanguageMachines/dimbl/releases/190947850", "release_id": 190947850, "date_created": "2024-12-16T10:46:11Z", "date_published": "2024-12-16T13:19:17Z", "assets": [{"url": "https://api.github.com/repos/LanguageMachines/dimbl/releases/assets/213688587", "name": "dimbl-0.18.tar.gz", "content_size": 467551, "content_url": "https://github.com/LanguageMachines/dimbl/releases/download/v0.18/dimbl-0.18.tar.gz", "encoding_format": "application/gzip", "upload_date": "2024-12-16T13:19:11Z", "download_count": 5}]}, "confidence": 1, "technique": "GitHub_API"}, {"result": {"type": "Release", "value": "https://api.github.com/repos/LanguageMachines/dimbl/releases/87703862", "tag": "v0.17", "name": "v0.17", "author": {"name": "kosloot", "type": "User"}, "description": "* adapted to newest Timbl (>= 6.8)\r\n* some code cleanup, more C++11 like\r\n* added GitHub action\r\n", "tarball_url": "https://api.github.com/repos/LanguageMachines/dimbl/tarball/v0.17", "zipball_url": "https://api.github.com/repos/LanguageMachines/dimbl/zipball/v0.17", "html_url": "https://github.com/LanguageMachines/dimbl/releases/tag/v0.17", "url": "https://api.github.com/repos/LanguageMachines/dimbl/releases/87703862", "release_id": 87703862, "date_created": "2023-01-02T15:02:59Z", "date_published": "2023-01-02T15:04:56Z", "assets": [{"url": "https://api.github.com/repos/LanguageMachines/dimbl/releases/assets/90255136", "name": "dimbl-0.17.tar.gz", "content_size": 450082, "content_url": "https://github.com/LanguageMachines/dimbl/releases/download/v0.17/dimbl-0.17.tar.gz", "encoding_format": "application/gzip", "upload_date": "2023-01-02T15:04:45Z", "download_count": 9}]}, "confidence": 1, "technique": "GitHub_API"}, {"result": {"type": "Release", "value": "https://api.github.com/repos/LanguageMachines/dimbl/releases/25525163", "tag": "v0.16", "name": "v0.16", "author": {"name": "kosloot", "type": "User"}, "description": "* better configuration (OpenMP and removed Boost)\r\n* some modernization.\r\n", "tarball_url": "https://api.github.com/repos/LanguageMachines/dimbl/tarball/v0.16", "zipball_url": "https://api.github.com/repos/LanguageMachines/dimbl/zipball/v0.16", "html_url": "https://github.com/LanguageMachines/dimbl/releases/tag/v0.16", "url": "https://api.github.com/repos/LanguageMachines/dimbl/releases/25525163", "release_id": 25525163, "date_created": "2020-04-15T11:21:24Z", "date_published": "2020-04-15T11:22:33Z", "assets": [{"url": "https://api.github.com/repos/LanguageMachines/dimbl/releases/assets/19819816", "name": "dimbl-0.16.tar.gz", "content_size": 434665, "content_url": "https://github.com/LanguageMachines/dimbl/releases/download/v0.16/dimbl-0.16.tar.gz", "encoding_format": "application/gzip", "upload_date": "2020-04-15T11:22:28Z", "download_count": 17}]}, "confidence": 1, "technique": "GitHub_API"}, {"result": {"type": "Release", "value": "https://api.github.com/repos/LanguageMachines/dimbl/releases/2445178", "tag": "v0.15", "name": "v0.15", "author": {"name": "kosloot", "type": "User"}, "description": "First release of Dimbl from GIT\n", "tarball_url": "https://api.github.com/repos/LanguageMachines/dimbl/tarball/v0.15", "zipball_url": "https://api.github.com/repos/LanguageMachines/dimbl/zipball/v0.15", "html_url": "https://github.com/LanguageMachines/dimbl/releases/tag/v0.15", "url": "https://api.github.com/repos/LanguageMachines/dimbl/releases/2445178", "release_id": 2445178, "date_created": "2016-01-14T13:24:12Z", "date_published": "2016-01-18T10:56:47Z", "assets": [{"url": "https://api.github.com/repos/LanguageMachines/dimbl/releases/assets/1220794", "name": "dimbl-0.15.tar.gz", "content_size": 409314, "content_url": "https://github.com/LanguageMachines/dimbl/releases/download/v0.15/dimbl-0.15.tar.gz", "encoding_format": "application/gzip", "upload_date": "2016-01-18T10:56:42Z", "download_count": 54}]}, "confidence": 1, "technique": "GitHub_API"}], "has_script_file": [{"result": {"value": "https://raw.githubusercontent.com/LanguageMachines/dimbl/master/bootstrap.sh", "type": "Url"}, "confidence": 1, "technique": "file_exploration"}, {"result": {"value": "https://raw.githubusercontent.com/LanguageMachines/dimbl/master/src/tst.sh", "type": "Url"}, "confidence": 1, "technique": "file_exploration"}], "readme_url": [{"result": {"value": "https://raw.githubusercontent.com/LanguageMachines/dimbl/master/README", "type": "Url"}, "confidence": 1, "technique": "file_exploration"}, {"result": {"value": "https://raw.githubusercontent.com/LanguageMachines/dimbl/master/README.md", "type": "Url"}, "confidence": 1, "technique": "file_exploration"}], "authors": [{"result": {"name": "Antal van den Bosch", "type": "Agent", "value": "Antal van den Bosch", "last_name": "van den Bosch", "given_name": "Antal"}, "confidence": 1, "technique": "file_exploration", "source": "https://raw.githubusercontent.com/LanguageMachines/dimbl/master/AUTHORS"}, {"result": {"name": "Ko van der Sloot", "type": "Agent", "value": "Ko van der Sloot", "last_name": "van der Sloot", "given_name": "Ko"}, "confidence": 1, "technique": "file_exploration", "source": "https://raw.githubusercontent.com/LanguageMachines/dimbl/master/AUTHORS"}], "continuous_integration": [{"result": {"value": "https://raw.githubusercontent.com/LanguageMachines/dimbl/master/.github/workflows/dimbl.yml", "type": "Url"}, "confidence": 1, "technique": "file_exploration"}, {"result": {"value": "https://raw.githubusercontent.com/LanguageMachines/dimbl/master/.github/workflows/cleanup.yml", "type": "Url"}, "confidence": 1, "technique": "file_exploration"}], "identifier": [{"result": {"type": "Url", "value": "https://zenodo.org/badge/latestdoi/9028755"}, "confidence": 1, "technique": "regular_expression", "source": "https://raw.githubusercontent.com/LanguageMachines/dimbl/master/README"}], "full_title": [{"result": {"type": "String", "value": "Distributed Tilburg Memory Based Learner"}, "confidence": 1, "technique": "regular_expression", "source": "https://raw.githubusercontent.com/LanguageMachines/dimbl/master/README"}], "repository_status": [{"result": {"type": "Url", "value": "https://www.repostatus.org/#active", "description": "Active \u2013 The project has reached a stable, usable state and is being actively developed."}, "confidence": 1, "technique": "regular_expression", "source": "https://raw.githubusercontent.com/LanguageMachines/dimbl/master/README"}], "logo": [{"result": {"type": "Url", "value": "http://applejack.science.ru.nl/lamabadge.php/dimbl"}, "confidence": 1, "technique": "regular_expression", "source": "https://raw.githubusercontent.com/LanguageMachines/dimbl/master/README"}]}